{
  "type_description_msg": {
    "type_description": {
      "type_name": "ros_robot_controller_msgs/msg/GetBusServoCmd",
      "fields": [
        {
          "name": "id",
          "type": {
            "type_id": 3,
            "capacity": 0,
            "string_capacity": 0,
            "nested_type_name": ""
          },
          "default_value": ""
        },
        {
          "name": "get_id",
          "type": {
            "type_id": 3,
            "capacity": 0,
            "string_capacity": 0,
            "nested_type_name": ""
          },
          "default_value": ""
        },
        {
          "name": "get_position",
          "type": {
            "type_id": 3,
            "capacity": 0,
            "string_capacity": 0,
            "nested_type_name": ""
          },
          "default_value": ""
        },
        {
          "name": "get_offset",
          "type": {
            "type_id": 3,
            "capacity": 0,
            "string_capacity": 0,
            "nested_type_name": ""
          },
          "default_value": ""
        },
        {
          "name": "get_voltage",
          "type": {
            "type_id": 3,
            "capacity": 0,
            "string_capacity": 0,
            "nested_type_name": ""
          },
          "default_value": ""
        },
        {
          "name": "get_temperature",
          "type": {
            "type_id": 3,
            "capacity": 0,
            "string_capacity": 0,
            "nested_type_name": ""
          },
          "default_value": ""
        },
        {
          "name": "get_position_limit",
          "type": {
            "type_id": 3,
            "capacity": 0,
            "string_capacity": 0,
            "nested_type_name": ""
          },
          "default_value": ""
        },
        {
          "name": "get_voltage_limit",
          "type": {
            "type_id": 3,
            "capacity": 0,
            "string_capacity": 0,
            "nested_type_name": ""
          },
          "default_value": ""
        },
        {
          "name": "get_max_temperature_limit",
          "type": {
            "type_id": 3,
            "capacity": 0,
            "string_capacity": 0,
            "nested_type_name": ""
          },
          "default_value": ""
        },
        {
          "name": "get_torque_state",
          "type": {
            "type_id": 3,
            "capacity": 0,
            "string_capacity": 0,
            "nested_type_name": ""
          },
          "default_value": ""
        }
      ]
    },
    "referenced_type_descriptions": []
  },
  "type_hashes": [
    {
      "type_name": "ros_robot_controller_msgs/msg/GetBusServoCmd",
      "hash_string": "RIHS01_23bebbe686ec0ead4187b91c9466467f744460310daa1d72c81d6059b90fdf78"
    }
  ]
}